avro_validator/__init__.py
avro_validator/avro_types.py
avro_validator/cli.py
avro_validator/schema.py
avro_validator-1.2.1.dist-info/LICENSE
avro_validator-1.2.1.dist-info/METADATA
avro_validator-1.2.1.dist-info/WHEEL
avro_validator-1.2.1.dist-info/entry_points.txt
avro_validator-1.2.1.dist-info/top_level.txt
avro_validator-1.2.1.dist-info/RECORD
