Metadata-Version: 2.1
Name: avro_validator
Version: 1.2.1
Summary: Pure python avro schema validator
Home-page: https://github.com/leocalm/avro_validator
Author: Leonardo de Campos Almeida
Author-email: leocalm@gmail.com
Project-URL: Repository, https://github.com/leocalm/avro_validator
Project-URL: Bug Reports, https://github.com/leocalm/avro_validator/issues
Project-URL: Documentation, https://avro-validator.readthedocs.io/
Keywords: avro schema
Classifier: Programming Language :: Python :: 3
Classifier: License :: OSI Approved :: MIT License
Classifier: Operating System :: OS Independent
Requires-Python: >=3.6
Provides-Extra: dev
Provides-Extra: docs
License-File: LICENSE
